BingImageCreator.py
BingImageCreator_fork-0.8.2.dist-info/LICENSE
BingImageCreator_fork-0.8.2.dist-info/METADATA
BingImageCreator_fork-0.8.2.dist-info/WHEEL
BingImageCreator_fork-0.8.2.dist-info/top_level.txt
BingImageCreator_fork-0.8.2.dist-info/RECORD
