Metadata-Version: 2.1
Name: BingImageCreator-fork
Version: 0.8.2
Summary: High quality image generation by Microsoft. Reverse engineered API.
Home-page: https://github.com/yihong0618/BingImageCreator
Author: Antonio Cheong, yihong0618
Author-email: acheong@student.dalat.org, zouzou0208@gmail.com
License: GNU General Public License v2.0
Project-URL: Bug Report, https://github.com/yihong0618/BingImageCreator/issues/new
Classifier: License :: OSI Approved :: GNU General Public License v2 (GPLv2)
Classifier: Intended Audience :: Developers
Classifier: Topic :: Software Development :: Libraries :: Python Modules
Classifier: Programming Language :: Python :: 3.8
Classifier: Programming Language :: Python :: 3.9
Classifier: Programming Language :: Python :: 3.10
Classifier: Programming Language :: Python :: 3.11
License-File: LICENSE
Requires-Dist: httpx
Requires-Dist: regex
Requires-Dist: requests
Requires-Dist: fake-useragent
Requires-Dist: curl-cffi
